iterative_ensemble_smoother/__init__.py
iterative_ensemble_smoother/_version.py
iterative_ensemble_smoother/esmda.py
iterative_ensemble_smoother/esmda_inversion.py
iterative_ensemble_smoother/experimental.py
iterative_ensemble_smoother/sies.py
iterative_ensemble_smoother/sies_inversion.py
iterative_ensemble_smoother/utils.py
iterative_ensemble_smoother-0.4.2.dist-info/licenses/COPYING
iterative_ensemble_smoother-0.4.2.dist-info/METADATA
iterative_ensemble_smoother-0.4.2.dist-info/WHEEL
iterative_ensemble_smoother-0.4.2.dist-info/top_level.txt
iterative_ensemble_smoother-0.4.2.dist-info/RECORD
