Metadata-Version: 2.4
Name: iterative_ensemble_smoother
Version: 0.4.2
Summary: A library for the iterative ensemble smoother algorithm.
Author-email: Equinor <fg_sib-scout@equinor.com>
Maintainer-email: Eivind Jahren <ejah@equinor.com>, Feda Curic <fcur@equinor.com>
License: GPL-3.0
Project-URL: Homepage, https://github.com/equinor/iterative_ensemble_smoother
Project-URL: Repository, https://github.com/equinor/iterative_ensemble_smoother
Project-URL: Bug Tracker, https://github.com/equinor/iterative_ensemble_smoother/issues
Project-URL: Documentation, https://iterative_ensemble_smoother.readthedocs.io/en/stable/
Classifier: Development Status :: 1 - Planning
Classifier: License :: OSI Approved :: GNU General Public License v3 or later (GPLv3+)
Classifier: Programming Language :: Python
Classifier: Programming Language :: Python :: 3.9
Classifier: Programming Language :: Python :: 3.10
Classifier: Programming Language :: Python :: 3.11
Classifier: Programming Language :: Python :: 3.12
Classifier: Programming Language :: Python :: 3.13
License-File: COPYING
Requires-Dist: numpy
Requires-Dist: scipy
Requires-Dist: joblib
Provides-Extra: doc
Requires-Dist: sphinx; extra == "doc"
Requires-Dist: setuptools; extra == "doc"
Requires-Dist: docutils; extra == "doc"
Requires-Dist: pydata_sphinx_theme; extra == "doc"
Requires-Dist: jupyter_sphinx; extra == "doc"
Requires-Dist: sphinxcontrib.bibtex; extra == "doc"
Requires-Dist: matplotlib; extra == "doc"
Requires-Dist: pygments; extra == "doc"
Requires-Dist: jupytext; extra == "doc"
Requires-Dist: pandas; extra == "doc"
Requires-Dist: p_tqdm; extra == "doc"
Requires-Dist: ipykernel; extra == "doc"
Requires-Dist: ipywidgets; extra == "doc"
Requires-Dist: numpydoc; extra == "doc"
Requires-Dist: scipy; extra == "doc"
Requires-Dist: jinja2; extra == "doc"
Requires-Dist: m2r2>=0.3.3; extra == "doc"
Requires-Dist: myst_nb; extra == "doc"
Requires-Dist: lxml_html_clean; extra == "doc"
Provides-Extra: dev
Requires-Dist: pytest; extra == "dev"
Requires-Dist: pytest-snapshot; extra == "dev"
Requires-Dist: pytest-memray; extra == "dev"
Requires-Dist: tox; extra == "dev"
Requires-Dist: pre-commit; extra == "dev"
Requires-Dist: matplotlib; extra == "dev"
Requires-Dist: scipy; extra == "dev"
Requires-Dist: mypy; extra == "dev"
Requires-Dist: pandas; extra == "dev"
Requires-Dist: p_tqdm; extra == "dev"
Requires-Dist: pylint; extra == "dev"
Dynamic: license-file
